Workbook

Sheet Methodology
A1: MODEL METHODOLOGY & DATA DICTIONARY
A2: How this model works — built to replicate enterprise vendor consolidation and variance analysis practices in regulated financial services
A3: IMPORTANT NOTE
A4: All data in this workbook is synthetic and created for demonstration purposes only. No actual employer, client, or proprietary data is used. The model structure, methodology, and analytical approach reflect professional financial modeling practices developed across 20+ years in commercial real estate finance, capital markets, and enterprise analytics.
A6: MODEL ARCHITECTURE
A7: This model is built in five interconnected tabs:
A8: 1. Executive Dashboard — KPI summary tiles + department savings by category. Built for C-suite consumption.
A9: 2. Variance Analysis — Month-by-month actual vs. budget vs. forecast by cost category. Designed for Department review cadence.
A10: 3. Consolidation Scenarios — Three scenario comparison (Conservative / Base / Aggressive) driven by assumption toggles.
A11: 4. Sensitivity Model — Two-variable sensitivity table showing net savings across a range of vendor reduction % and discount rate combinations.
A12: 5. Methodology (this tab) — Model documentation, data dictionary, and color-coding guide.
A14: COLOR CODING (INDUSTRY STANDARD)
... A33: Step 5 — Close the loop: 'The models were built once the underlying data was governed. The $180M outcome was possible because leadership trusted the data it was built on. Without the reconciliation work first, the models would have been rejected as unreliable.'

Sheet Executive Dashboard
A1: ENTERPRISE COST OPTIMIZATION — EXECUTIVE SUMMARY
A2: Vendor Consolidation Analysis | FY2022–FY2023 | All figures in $M | Synthetic demonstration data
A4: Total Identified Savings | C4: Vendors Consolidated | E4: Audit Escalations | G4: Stakeholders Aligned
A5: $180.4M | C5: 47 → 18 | E5: Zero | G5: 150+
A6: +12.3% vs. Target | C6: 62% Reduction | E6: 3-Year Record | G6: Finance | Risk | Ops
A9: SAVINGS BY DEPARTMENT
A10: Department | B10: Baseline Spend ($M) | C10: Post-Consolidation ($M) | D10: Savings ($M) | E10: Savings % | F10: Status
A11: Finance | B11: 142.3 | C11: 102.8 | D11: =B11-C11 -> 39.5 | E11: =D11/B11 -> 0.27758257 | F11: ✓ Complete
A12: Risk | B12: 98.7 | C12: 76.4 | D12: =B12-C12 -> 22.3 | E12: =D12/B12 -> 0.22593718 | F12: ✓ Complete
A13: Operations | B13: 187.6 | C13: 149 | D13: =B13-C13 -> 38.6 | E13: =D13/B13 -> 0.20575693 | F13: ✓ Complete
A14: TOTAL | B14: 428.6 | C14: 328.2 | D14: =B14-C14 -> 100.4 | E14: =D14/B14 -> 0.23425105
A16: Methodology: Baseline = FY2022 actual vendor spend by department. Post-consolidation = projected spend after vendor rationalization under Scenario B (62% vendor reduction). Variance validated against Finance, Risk, and Operations source data with reconciliation controls.

Sheet Variance Analysis - Finance
A1: DEPARTMENT-LEVEL COST VARIANCE ANALYSIS
A2: Actual vs. Budget vs. Forecast by Cost Category | FY2022 Full Year | $000s | Dept Baseline: $142.3M
A4: FINANCE DEPARTMENT
A5: Cost Category | B5: Jan | C5: Feb | D5: Mar | E5: Apr | F5: May | G5: Jun | H5: Jul | I5: Aug | J5: Sep | K5: Oct | L5: Nov | M5: Dec | N5: FY Total
A6: Budget
A7: Vendor Licensing | B7: 2335 | C7: 860 | D7: 1460 | E7: 1336 | F7: 2568 | G7: 2424 | H7: 2941 | I7: 1009 | J7: 1813 | K7: 872 | L7: 1325 | M7: 2013 | N7: =SUM(B7:M7) -> 20956
A8: Professional Services | B8: 864 | C8: 1277 | D8: 2360 | E8: 2108 | F8: 1329 | G8: 2214 | H8: 2743 | I8: 816 | J8: 2734 | K8: 2476 | L8: 1617 | M8: 1173 | N8: =SUM(B8:M8) -> 21711
A9: Software & Platforms | B9: 3097 | C9: 1608 | D9: 1023 | E9: 1032 | F9: 2834 | G9: 2249 | H9: 2737 | I9: 2551 | J9: 2087 | K9: 3135 | L9: 1708 | M9: 2125 | N9: =SUM(B9:M9) -> 26186
A10: Infrastructure & Hosting | B10: 2791 | C10: 2284 | D10: 2868 | E10: 2186 | F10: 2491 | G10: 910 | H10: 1347 | I10: 1495 | J10: 992 | K10: 1359 | L10: 1042 | M10: 1467 | N10: =SUM(B10:M10) -> 21232
A11: Contracted Labor | B11: 2326 | C11: 1676 | D11: 1688 | E11: 1303 | F11: 1441 | G11: 3048 | H11: 2355 | I11: 2262 | J11: 1211 | K11: 2550 | L11: 1192 | M11: 1711 | N11: =SUM(B11:M11) -> 22763
A12: Miscellaneous Vendor | B12: 3175 | C12: 2336 | D12: 2137 | E12: 2443 | F12: 2823 | G12: 2662 | H12: 1350 | I12: 877 | J12: 1557 | K12: 1443 | L12: 1306 | M12: 3063 | N12: =SUM(B12:M12) -> 25172
A14: Actual | B14: Jan | C14: Feb | D14: Mar | E14: Apr | F14: May | G14: Jun | H14: Jul | I14: Aug | J14: Sep | K14: Oct | L14: Nov | M14: Dec | N14: FY Total
A15: Vendor Licensing | B15: =B7*(1+0.095) -> 2556.825 | C15: =C7*(1+-0.017) -> 845.38 | D15: =D7*(1+0.051) -> 1534.46 | E15: =E7*(1+-0.001) -> 1334.664 | F15: =F7*(1+0.103) -> 2832.504 | G15: =G7*(1+0.012) -> 2453.088 | H15: =H7*(1+-0.027) -> 2861.593 | I15: =I7*(1+-0.031) -> 977.721 | J15: =J7*(1+0.032) -> 1871.016 | K15: =K7*(1+-0.027) -> 848.456 | L15: =L7*(1+0.037) -> 1374.025 | M15: =M7*(1+0.1) -> 2214.3 | N15: =SUM(B15:M15) -> 21704.032
A16: Professional Services | B16: =B8*(1+0) -> 864 | C16: =C8*(1+-0.036) -> 1231.028 | D16: =D8*(1+0.12) -> 2643.2 | E16: =E8*(1+0.022) -> 2154.376 | F16: =F8*(1+-0.062) -> 1246.602 | G16: =G8*(1+-0.071) -> 2056.806 | H16: =H8*(1+-0.058) -> 2583.906 | I16: =I8*(1+0.045) -> 852.72 | J16: =J8*(1+0.078) -> 2947.252 | K16: =K8*(1+0.004) -> 2485.904 | L16: =L8*(1+-0.067) -> 1508.661 | M16: =M8*(1+-0.004) -> 1168.308 | N16: =SUM(B16:M16) -> 21742.763
A17: Software & Platforms | B17: =B9*(1+0.119) -> 3465.543 | C17: =C9*(1+0.026) -> 1649.808 | D17: =D9*(1+0.114) -> 1139.622 | E17: =E9*(1+0.092) -> 1126.944 | F17: =F9*(1+-0.078) -> 2612.948 | G17: =G9*(1+0.064) -> 2392.936 | H17: =H9*(1+0.056) -> 2890.272 | I17: =I9*(1+0.027) -> 2619.877 | J17: =J9*(1+-0.027) -> 2030.651 | K17: =K9*(1+0.048) -> 3285.48 | L17: =L9*(1+-0.058) -> 1608.936 | M17: =M9*(1+0.007) -> 2139.875 | N17: =SUM(B17:M17) -> 26962.892
A18: Infrastructure & Hosting | B18: =B10*(1+0.011) -> 2821.701 | C18: =C10*(1+0.111) -> 2537.524 | D18: =D10*(1+0.095) -> 3140.46 | E18: =E10*(1+-0.027) -> 2126.978 | F18: =F10*(1+0.02) -> 2540.82 | G18: =G10*(1+-0.044) -> 869.96 | H18: =H10*(1+0.103) -> 1485.741 | I18: =I10*(1+0.094) -> 1635.53 | J18: =J10*(1+-0.02) -> 972.16 | K18: =K10*(1+0.048) -> 1424.232 | L18: =L10*(1+0.042) -> 1085.764 | M18: =M10*(1+-0.049) -> 1395.117 | N18: =SUM(B18:M18) -> 22035.987
A19: Contracted Labor | B19: =B11*(1+0.073) -> 2495.798 | C19: =C11*(1+0.028) -> 1722.928 | D19: =D11*(1+0.076) -> 1816.288 | E19: =E11*(1+0.026) -> 1336.878 | F19: =F11*(1+-0.08) -> 1325.72 | G19: =G11*(1+-0.015) -> 3002.28 | H19: =H11*(1+-0.076) -> 2176.02 | I19: =I11*(1+0.106) -> 2501.772 | J19: =J11*(1+0.096) -> 1327.256 | K19: =K11*(1+0.086) -> 2769.3 | L19: =L11*(1+-0.018) -> 1170.544 | M19: =M11*(1+-0.068) -> 1594.652 | N19: =SUM(B19:M19) -> 23239.436
A20: Miscellaneous Vendor | B20: =B12*(1+0.096) -> 3479.8 | C20: =C12*(1+0.109) -> 2590.624 | D20: =D12*(1+-0.063) -> 2002.369 | E20: =E12*(1+0.017) -> 2484.531 | F20: =F12*(1+-0.066) -> 2636.682 | G20: =G12*(1+0.072) -> 2853.664 | H20: =H12*(1+0.073) -> 1448.55 | I20: =I12*(1+-0.054) -> 829.642 | J20: =J12*(1+0.015) -> 1580.355 | K20: =K12*(1+0.03) -> 1486.29 | L20: =L12*(1+-0.027) -> 1270.738 | M20: =M12*(1+0.094) -> 3350.922 | N20: =SUM(B20:M20) -> 26014.167
A22: Variance $ | B22: Jan | C22: Feb | D22: Mar | E22: Apr | F22: May | G22: Jun | H22: Jul | I22: Aug | J22: Sep | K22: Oct | L22: Nov | M22: Dec | N22: FY Total
A23: Vendor Licensing | B23: =B15-B7 -> 221.825 | C23: =C15-C7 -> -14.62 | D23: =D15-D7 -> 74.46 | E23: =E15-E7 -> -1.336 | F23: =F15-F7 -> 264.504 | G23: =G15-G7 -> 29.088 | H23: =H15-H7 -> -79.407 | I23: =I15-I7 -> -31.279 | ... N23: =N15-N7 -> 748.032
A24: Professional Services | B24: =B16-B8 -> 0 | C24: =C16-C8 -> -45.972 | D24: =D16-D8 -> 283.2 | E24: =E16-E8 -> 46.376 | F24: =F16-F8 -> -82.398 | G24: =G16-G8 -> -157.194 | H24: =H16-H8 -> -159.094 | I24: =I16-I8 -> 36.72 | ... N24: =N16-N8 -> 31.763
A25: Software & Platforms | B25: =B17-B9 -> 368.543 | C25: =C17-C9 -> 41.808 | D25: =D17-D9 -> 116.622 | E25: =E17-E9 -> 94.944 | F25: =F17-F9 -> -221.052 | G25: =G17-G9 -> 143.936 | H25: =H17-H9 -> 153.272 | I25: =I17-I9 -> 68.877 | ... N25: =N17-N9 -> 776.892
A26: Infrastructure & Hosting | B26: =B18-B10 -> 30.701 | C26: =C18-C10 -> 253.524 | D26: =D18-D10 -> 272.46 | E26: =E18-E10 -> -59.022 | F26: =F18-F10 -> 49.82 | G26: =G18-G10 -> -40.04 | H26: =H18-H10 -> 138.741 | I26: =I18-I10 -> 140.53 | ... N26: =N18-N10 -> 803.987
A27: Contracted Labor | B27: =B19-B11 -> 169.798 | C27: =C19-C11 -> 46.928 | D27: =D19-D11 -> 128.288 | E27: =E19-E11 -> 33.878 | F27: =F19-F11 -> -115.28 | G27: =G19-G11 -> -45.72 | H27: =H19-H11 -> -178.98 | I27: =I19-I11 -> 239.772 | ... N27: =N19-N11 -> 476.436
A28: Miscellaneous Vendor | B28: =B20-B12 -> 304.8 | C28: =C20-C12 -> 254.624 | D28: =D20-D12 -> -134.631 | E28: =E20-E12 -> 41.531 | F28: =F20-F12 -> -186.318 | G28: =G20-G12 -> 191.664 | H28: =H20-H12 -> 98.55 | I28: =I20-I12 -> -47.358 | ... N28: =N20-N12 -> 842.167
A30: Variance % | B30: Jan | C30: Feb | D30: Mar | E30: Apr | F30: May | G30: Jun | H30: Jul | I30: Aug | J30: Sep | K30: Oct | L30: Nov | M30: Dec | N30: FY Total
A31: Vendor Licensing | B31: =IFERROR(B23/B7,0) -> 0.095 | C31: =IFERROR(C23/C7,0) -> -0.017 | D31: =IFERROR(D23/D7,0) -> 0.051 | E31: =IFERROR(E23/E7,0) -> -0.001 | F31: =IFERROR(F23/F7,0) -> 0.103 | G31: =IFERROR(G23/G7,0) -> 0.012 | H31: =IFERROR(H23/H7,0) -> -0.027 | I31: =IFERROR(I23/I7,0) -> -0.031 | ... N31: =IFERROR(N23/N7,0) -> 0.035695362
A32: Professional Services | B32: =IFERROR(B24/B8,0) -> 0 | C32: =IFERROR(C24/C8,0) -> -0.036 | D32: =IFERROR(D24/D8,0) -> 0.12 | E32: =IFERROR(E24/E8,0) -> 0.022 | F32: =IFERROR(F24/F8,0) -> -0.062 | G32: =IFERROR(G24/G8,0) -> -0.071 | H32: =IFERROR(H24/H8,0) -> -0.058 | I32: =IFERROR(I24/I8,0) -> 0.045 | ... N32: =IFERROR(N24/N8,0) -> 0.0014629911
A33: Software & Platforms | B33: =IFERROR(B25/B9,0) -> 0.119 | C33: =IFERROR(C25/C9,0) -> 0.026 | D33: =IFERROR(D25/D9,0) -> 0.114 | E33: =IFERROR(E25/E9,0) -> 0.092 | F33: =IFERROR(F25/F9,0) -> -0.078 | G33: =IFERROR(G25/G9,0) -> 0.064 | H33: =IFERROR(H25/H9,0) -> 0.056 | I33: =IFERROR(I25/I9,0) -> 0.027 | ... N33: =IFERROR(N25/N9,0) -> 0.02966822
A34: Infrastructure & Hosting | B34: =IFERROR(B26/B10,0) -> 0.011 | C34: =IFERROR(C26/C10,0) -> 0.111 | D34: =IFERROR(D26/D10,0) -> 0.095 | E34: =IFERROR(E26/E10,0) -> -0.027 | F34: =IFERROR(F26/F10,0) -> 0.02 | G34: =IFERROR(G26/G10,0) -> -0.044 | H34: =IFERROR(H26/H10,0) -> 0.103 | I34: =IFERROR(I26/I10,0) -> 0.094 | ... N34: =IFERROR(N26/N10,0) -> 0.037866758
A35: Contracted Labor | B35: =IFERROR(B27/B11,0) -> 0.073 | C35: =IFERROR(C27/C11,0) -> 0.028 | D35: =IFERROR(D27/D11,0) -> 0.076 | E35: =IFERROR(E27/E11,0) -> 0.026 | F35: =IFERROR(F27/F11,0) -> -0.08 | G35: =IFERROR(G27/G11,0) -> -0.015 | H35: =IFERROR(H27/H11,0) -> -0.076 | I35: =IFERROR(I27/I11,0) -> 0.106 | ... N35: =IFERROR(N27/N11,0) -> 0.020930282
A36: Miscellaneous Vendor | B36: =IFERROR(B28/B12,0) -> 0.096 | C36: =IFERROR(C28/C12,0) -> 0.109 | D36: =IFERROR(D28/D12,0) -> -0.063 | E36: =IFERROR(E28/E12,0) -> 0.017 | F36: =IFERROR(F28/F12,0) -> -0.066 | G36: =IFERROR(G28/G12,0) -> 0.072 | H36: =IFERROR(H28/H12,0) -> 0.073 | I36: =IFERROR(I28/I12,0) -> -0.054 | ... N36: =IFERROR(N28/N12,0) -> 0.033456499

Sheet Variance Analysis - Risk
A1: DEPARTMENT-LEVEL COST VARIANCE ANALYSIS
A2: Actual vs. Budget vs. Forecast by Cost Category | FY2022 Full Year | $000s | Dept Baseline: $98.7M
A4: RISK DEPARTMENT
A5: Cost Category | B5: Jan | C5: Feb | D5: Mar | E5: Apr | F5: May | G5: Jun | H5: Jul | I5: Aug | J5: Sep | K5: Oct | L5: Nov | M5: Dec | N5: FY Total
A6: Budget
A7: Vendor Licensing | B7: 1620 | C7: 597 | D7: 1013 | E7: 927 | F7: 1781 | G7: 1681 | H7: 2040 | I7: 700 | J7: 1258 | K7: 605 | L7: 919 | M7: 1396 | N7: =SUM(B7:M7) -> 14537
A8: Professional Services | B8: 599 | C8: 886 | D8: 1637 | E8: 1462 | F8: 922 | G8: 1536 | H8: 1903 | I8: 566 | J8: 1896 | K8: 1717 | L8: 1122 | M8: 814 | N8: =SUM(B8:M8) -> 15060
A9: Software & Platforms | B9: 2148 | C9: 1115 | D9: 710 | E9: 716 | F9: 1966 | G9: 1560 | H9: 1898 | I9: 1769 | J9: 1448 | K9: 2174 | L9: 1185 | M9: 1474 | N9: =SUM(B9:M9) -> 18163
A10: Infrastructure & Hosting | B10: 1936 | C10: 1584 | D10: 1989 | E10: 1516 | F10: 1728 | G10: 631 | H10: 934 | I10: 1037 | J10: 688 | K10: 943 | L10: 723 | M10: 1018 | N10: =SUM(B10:M10) -> 14727
A11: Contracted Labor | B11: 1613 | C11: 1162 | D11: 1171 | E11: 904 | F11: 999 | G11: 2114 | H11: 1633 | I11: 1569 | J11: 840 | K11: 1769 | L11: 827 | M11: 1187 | N11: =SUM(B11:M11) -> 15788
A12: Miscellaneous Vendor | B12: 2202 | C12: 1620 | D12: 1482 | E12: 1694 | F12: 1958 | G12: 1846 | H12: 936 | I12: 608 | J12: 1080 | K12: 1001 | L12: 906 | M12: 2125 | N12: =SUM(B12:M12) -> 17458
A14: Actual | B14: Jan | C14: Feb | D14: Mar | E14: Apr | F14: May | G14: Jun | H14: Jul | I14: Aug | J14: Sep | K14: Oct | L14: Nov | M14: Dec | N14: FY Total
A15: Vendor Licensing | B15: =B7*(1+0.082) -> 1752.84 | C15: =C7*(1+-0.024) -> 582.672 | D15: =D7*(1+0.067) -> 1080.871 | E15: =E7*(1+0.011) -> 937.197 | F15: =F7*(1+0.091) -> 1943.071 | G15: =G7*(1+-0.018) -> 1650.742 | H15: =H7*(1+0.043) -> 2127.72 | I15: =I7*(1+-0.052) -> 663.6 | J15: =J7*(1+0.028) -> 1293.224 | K15: =K7*(1+-0.019) -> 593.505 | L15: =L7*(1+0.055) -> 969.545 | M15: =M7*(1+0.087) -> 1517.452 | N15: =SUM(B15:M15) -> 15112.439
A16: Professional Services | B16: =B8*(1+0.115) -> 667.885 | C16: =C8*(1+0.032) -> 914.352 | D16: =D8*(1+-0.041) -> 1569.883 | E16: =E8*(1+0.078) -> 1576.036 | F16: =F8*(1+0.019) -> 939.518 | G16: =G8*(1+-0.063) -> 1439.232 | H16: =H8*(1+0.094) -> 2081.882 | I16: =I8*(1+0.021) -> 577.886 | J16: =J8*(1+-0.038) -> 1823.952 | K16: =K8*(1+0.047) -> 1797.699 | L16: =L8*(1+-0.012) -> 1108.536 | M16: =M8*(1+0.033) -> 840.862 | N16: =SUM(B16:M16) -> 15337.723
A17: Software & Platforms | B17: =B9*(1+-0.027) -> 2090.004 | C17: =C9*(1+0.088) -> 1213.12 | D17: =D9*(1+0.054) -> 748.34 | E17: =E9*(1+-0.019) -> 702.396 | F17: =F9*(1+0.103) -> 2168.498 | G17: =G9*(1+0.041) -> 1623.96 | H17: =H9*(1+-0.033) -> 1835.366 | I17: =I9*(1+0.076) -> 1903.444 | J17: =J9*(1+0.017) -> 1472.616 | K17: =K9*(1+-0.044) -> 2078.344 | L17: =L9*(1+0.062) -> 1258.47 | M17: =M9*(1+0.009) -> 1487.266 | N17: =SUM(B17:M17) -> 18581.824
A18: Infrastructure & Hosting | B18: =B10*(1+0.039) -> 2011.504 | C18: =C10*(1+-0.051) -> 1503.216 | D18: =D10*(1+0.112) -> 2211.768 | E18: =E10*(1+0.023) -> 1550.868 | F18: =F10*(1+-0.016) -> 1700.352 | G18: =G10*(1+0.084) -> 684.004 | H18: =H10*(1+0.027) -> 959.218 | I18: =I10*(1+-0.039) -> 996.557 | J18: =J10*(1+0.093) -> 751.984 | K18: =K10*(1+0.011) -> 953.373 | L18: =L10*(1+-0.028) -> 702.756 | M18: =M10*(1+0.065) -> 1084.17 | N18: =SUM(B18:M18) -> 15109.77
A19: Contracted Labor | B19: =B11*(1+0.067) -> 1721.071 | C19: =C11*(1+0.018) -> 1182.916 | D19: =D11*(1+-0.073) -> 1085.517 | E19: =E11*(1+0.041) -> 941.064 | F19: =F11*(1+0.086) -> 1084.914 | G19: =G11*(1+-0.024) -> 2063.264 | H19: =H11*(1+0.052) -> 1717.916 | I19: =I11*(1+0.031) -> 1617.639 | J19: =J11*(1+-0.047) -> 800.52 | K19: =K11*(1+0.089) -> 1926.441 | L19: =L11*(1+0.013) -> 837.751 | M19: =M11*(1+-0.056) -> 1120.528 | N19: =SUM(B19:M19) -> 16099.541
A20: Miscellaneous Vendor | B20: =B12*(1+0.044) -> 2298.888 | C20: =C12*(1+0.091) -> 1767.42 | D20: =D12*(1+-0.028) -> 1440.504 | E20: =E12*(1+0.063) -> 1800.722 | F20: =F12*(1+-0.081) -> 1799.402 | G20: =G12*(1+0.037) -> 1914.302 | H20: =H12*(1+0.072) -> 1003.392 | I20: =I12*(1+-0.019) -> 596.448 | J20: =J12*(1+0.048) -> 1131.84 | K20: =K12*(1+0.026) -> 1027.026 | L20: =L12*(1+-0.041) -> 868.854 | M20: =M12*(1+0.083) -> 2301.375 | N20: =SUM(B20:M20) -> 17950.173
A22: Variance $ | B22: Jan | C22: Feb | D22: Mar | E22: Apr | F22: May | G22: Jun | H22: Jul | I22: Aug | J22: Sep | K22: Oct | L22: Nov | M22: Dec | N22: FY Total
A23: Vendor Licensing | B23: =B15-B7 -> 132.84 | C23: =C15-C7 -> -14.328 | D23: =D15-D7 -> 67.871 | E23: =E15-E7 -> 10.197 | F23: =F15-F7 -> 162.071 | G23: =G15-G7 -> -30.258 | H23: =H15-H7 -> 87.72 | I23: =I15-I7 -> -36.4 | ... M23: =M15-M7 -> 121.452 | N23: =SUM(B23:M23) -> 575.439
A24: Professional Services | B24: =B16-B8 -> 68.885 | C24: =C16-C8 -> 28.352 | D24: =D16-D8 -> -67.117 | E24: =E16-E8 -> 114.036 | F24: =F16-F8 -> 17.518 | G24: =G16-G8 -> -96.768 | H24: =H16-H8 -> 178.882 | I24: =I16-I8 -> 11.886 | ... M24: =M16-M8 -> 26.862 | N24: =SUM(B24:M24) -> 277.723
A25: Software & Platforms | B25: =B17-B9 -> -57.996 | C25: =C17-C9 -> 98.12 | D25: =D17-D9 -> 38.34 | E25: =E17-E9 -> -13.604 | F25: =F17-F9 -> 202.498 | G25: =G17-G9 -> 63.96 | H25: =H17-H9 -> -62.634 | I25: =I17-I9 -> 134.444 | ... M25: =M17-M9 -> 13.266 | N25: =SUM(B25:M25) -> 418.824
A26: Infrastructure & Hosting | B26: =B18-B10 -> 75.504 | C26: =C18-C10 -> -80.784 | D26: =D18-D10 -> 222.768 | E26: =E18-E10 -> 34.868 | F26: =F18-F10 -> -27.648 | G26: =G18-G10 -> 53.004 | H26: =H18-H10 -> 25.218 | I26: =I18-I10 -> -40.443 | ... M26: =M18-M10 -> 66.17 | N26: =SUM(B26:M26) -> 382.77
A27: Contracted Labor | B27: =B19-B11 -> 108.071 | C27: =C19-C11 -> 20.916 | D27: =D19-D11 -> -85.483 | E27: =E19-E11 -> 37.064 | F27: =F19-F11 -> 85.914 | G27: =G19-G11 -> -50.736 | H27: =H19-H11 -> 84.916 | I27: =I19-I11 -> 48.639 | ... M27: =M19-M11 -> -66.472 | N27: =SUM(B27:M27) -> 311.541
A28: Miscellaneous Vendor | B28: =B20-B12 -> 96.888 | C28: =C20-C12 -> 147.42 | D28: =D20-D12 -> -41.496 | E28: =E20-E12 -> 106.722 | F28: =F20-F12 -> -158.598 | G28: =G20-G12 -> 68.302 | H28: =H20-H12 -> 67.392 | I28: =I20-I12 -> -11.552 | ... M28: =M20-M12 -> 176.375 | N28: =SUM(B28:M28) -> 492.173
A30: Variance % | B30: Jan | C30: Feb | D30: Mar | E30: Apr | F30: May | G30: Jun | H30: Jul | I30: Aug | J30: Sep | K30: Oct | L30: Nov | M30: Dec | N30: FY Total
A31: Vendor Licensing | B31: =IFERROR(B23/B7,0) -> 0.082 | C31: =IFERROR(C23/C7,0) -> -0.024 | D31: =IFERROR(D23/D7,0) -> 0.067 | E31: =IFERROR(E23/E7,0) -> 0.011 | F31: =IFERROR(F23/F7,0) -> 0.091 | G31: =IFERROR(G23/G7,0) -> -0.018 | H31: =IFERROR(H23/H7,0) -> 0.043 | I31: =IFERROR(I23/I7,0) -> -0.052 | ... N31: =IFERROR(N23/N7,0) -> 0.03958444
A32: Professional Services | B32: =IFERROR(B24/B8,0) -> 0.115 | C32: =IFERROR(C24/C8,0) -> 0.032 | D32: =IFERROR(D24/D8,0) -> -0.041 | E32: =IFERROR(E24/E8,0) -> 0.078 | F32: =IFERROR(F24/F8,0) -> 0.019 | G32: =IFERROR(G24/G8,0) -> -0.063 | H32: =IFERROR(H24/H8,0) -> 0.094 | I32: =IFERROR(I24/I8,0) -> 0.021 | ... N32: =IFERROR(N24/N8,0) -> 0.018441102
A33: Software & Platforms | B33: =IFERROR(B25/B9,0) -> -0.027 | C33: =IFERROR(C25/C9,0) -> 0.088 | D33: =IFERROR(D25/D9,0) -> 0.054 | E33: =IFERROR(E25/E9,0) -> -0.019 | F33: =IFERROR(F25/F9,0) -> 0.103 | G33: =IFERROR(G25/G9,0) -> 0.041 | H33: =IFERROR(H25/H9,0) -> -0.033 | I33: =IFERROR(I25/I9,0) -> 0.076 | ... N33: =IFERROR(N25/N9,0) -> 0.023059186
A34: Infrastructure & Hosting | B34: =IFERROR(B26/B10,0) -> 0.039 | C34: =IFERROR(C26/C10,0) -> -0.051 | D34: =IFERROR(D26/D10,0) -> 0.112 | E34: =IFERROR(E26/E10,0) -> 0.023 | F34: =IFERROR(F26/F10,0) -> -0.016 | G34: =IFERROR(G26/G10,0) -> 0.084 | H34: =IFERROR(H26/H10,0) -> 0.027 | I34: =IFERROR(I26/I10,0) -> -0.039 | ... N34: =IFERROR(N26/N10,0) -> 0.025991037
A35: Contracted Labor | B35: =IFERROR(B27/B11,0) -> 0.067 | C35: =IFERROR(C27/C11,0) -> 0.018 | D35: =IFERROR(D27/D11,0) -> -0.073 | E35: =IFERROR(E27/E11,0) -> 0.041 | F35: =IFERROR(F27/F11,0) -> 0.086 | G35: =IFERROR(G27/G11,0) -> -0.024 | H35: =IFERROR(H27/H11,0) -> 0.052 | I35: =IFERROR(I27/I11,0) -> 0.031 | ... N35: =IFERROR(N27/N11,0) -> 0.019732772
A36: Miscellaneous Vendor | B36: =IFERROR(B28/B12,0) -> 0.044 | C36: =IFERROR(C28/C12,0) -> 0.091 | D36: =IFERROR(D28/D12,0) -> -0.028 | E36: =IFERROR(E28/E12,0) -> 0.063 | F36: =IFERROR(F28/F12,0) -> -0.081 | G36: =IFERROR(G28/G12,0) -> 0.037 | H36: =IFERROR(H28/H12,0) -> 0.072 | I36: =IFERROR(I28/I12,0) -> -0.019 | ... N36: =IFERROR(N28/N12,0) -> 0.028191832
A38: Note: Actual figures calculated as Budget × (1 + monthly variance rate). Variance rates are synthetic demonstration values embedded in formulas. In a production model these would be sourced from the GL and stored in a separate assumptions table with reconciliation controls.

Sheet Variance Analysis - Ops
A1: DEPARTMENT-LEVEL COST VARIANCE ANALYSIS
A2: Actual vs. Budget vs. Forecast by Cost Category | FY2022 Full Year | $000s | Dept Baseline: $187.6M
A4: OPERATIONS DEPARTMENT
A5: Cost Category | B5: Jan | C5: Feb | D5: Mar | E5: Apr | F5: May | G5: Jun | H5: Jul | I5: Aug | J5: Sep | K5: Oct | L5: Nov | M5: Dec | N5: FY Total
A6: Budget
A7: Vendor Licensing | B7: 3078 | C7: 1134 | D7: 1925 | E7: 1761 | F7: 3386 | G7: 3196 | H7: 3877 | I7: 1330 | J7: 2390 | K7: 1150 | L7: 1747 | M7: 2654 | N7: =SUM(B7:M7) -> 27628
A8: Professional Services | B8: 1139 | C8: 1684 | D8: 3111 | E8: 2779 | F8: 1752 | G8: 2919 | H8: 3616 | I8: 1076 | J8: 3604 | K8: 3264 | L8: 2132 | M8: 1546 | N8: =SUM(B8:M8) -> 28622
A9: Software & Platforms | B9: 4083 | C9: 2120 | D9: 1349 | E9: 1361 | F9: 3736 | G9: 2965 | H9: 3608 | I9: 3363 | J9: 2751 | K9: 4133 | L9: 2252 | M9: 2801 | N9: =SUM(B9:M9) -> 34522
A10: Infrastructure & Hosting | B10: 3679 | C10: 3011 | D10: 3781 | E10: 2882 | F10: 3284 | G10: 1200 | H10: 1776 | I10: 1971 | J10: 1308 | K10: 1792 | L10: 1374 | M10: 1934 | N10: =SUM(B10:M10) -> 27992
A11: Contracted Labor | B11: 3066 | C11: 2210 | D11: 2225 | E11: 1718 | F11: 1900 | G11: 4018 | H11: 3105 | I11: 2982 | J11: 1597 | K11: 3362 | L11: 1571 | M11: 2256 | N11: =SUM(B11:M11) -> 30010
A12: Miscellaneous Vendor | B12: 4186 | C12: 3080 | D12: 2817 | E12: 3221 | F12: 3722 | G12: 3509 | H12: 1780 | I12: 1156 | J12: 2053 | K12: 1902 | L12: 1722 | M12: 4038 | N12: =SUM(B12:M12) -> 33186
A14: Actual | B14: Jan | C14: Feb | D14: Mar | E14: Apr | F14: May | G14: Jun | H14: Jul | I14: Aug | J14: Sep | K14: Oct | L14: Nov | M14: Dec | N14: FY Total
A15: Vendor Licensing | B15: =B7*(1+0.051) -> 3234.978 | C15: =C7*(1+-0.038) -> 1090.908 | D15: =D7*(1+0.094) -> 2105.95 | E15: =E7*(1+0.027) -> 1808.547 | F15: =F7*(1+-0.065) -> 3165.91 | G15: =G7*(1+0.083) -> 3461.268 | H15: =H7*(1+0.016) -> 3939.032 | I15: =I7*(1+-0.042) -> 1274.14 | J15: =J7*(1+0.071) -> 2559.69 | K15: =K7*(1+0.033) -> 1187.95 | L15: =L7*(1+-0.019) -> 1713.807 | M15: =M7*(1+0.112) -> 2951.248 | N15: =SUM(B15:M15) -> 28493.428
A16: Professional Services | B16: =B8*(1+-0.019) -> 1117.359 | C16: =C8*(1+0.073) -> 1806.932 | D16: =D8*(1+0.038) -> 3229.218 | E16: =E8*(1+-0.054) -> 2628.934 | F16: =F8*(1+0.091) -> 1911.432 | G16: =G8*(1+0.022) -> 2983.218 | H16: =H8*(1+0.067) -> 3858.272 | I16: =I8*(1+-0.031) -> 1042.644 | J16: =J8*(1+0.048) -> 3776.992 | K16: =K8*(1+0.016) -> 3316.224 | L16: =L8*(1+-0.083) -> 1955.044 | M16: =M8*(1+0.044) -> 1614.024 | N16: =SUM(B16:M16) -> 29240.293
A17: Software & Platforms | B17: =B9*(1+0.087) -> 4438.221 | C17: =C9*(1+0.014) -> 2149.68 | D17: =D9*(1+-0.052) -> 1278.852 | E17: =E9*(1+0.096) -> 1491.656 | F17: =F9*(1+0.028) -> 3840.608 | G17: =G9*(1+-0.037) -> 2855.295 | H17: =H9*(1+0.081) -> 3900.248 | I17: =I9*(1+0.043) -> 3507.609 | J17: =J9*(1+-0.026) -> 2679.474 | K17: =K9*(1+0.058) -> 4372.714 | L17: =L9*(1+0.009) -> 2272.268 | M17: =M9*(1+-0.071) -> 2602.129 | N17: =SUM(B17:M17) -> 35388.754
A18: Infrastructure & Hosting | B18: =B10*(1+0.023) -> 3763.617 | C18: =C10*(1+0.104) -> 3324.144 | D18: =D10*(1+-0.041) -> 3625.979 | E18: =E10*(1+0.017) -> 2930.994 | F18: =F10*(1+0.076) -> 3533.584 | G18: =G10*(1+-0.053) -> 1136.4 | H18: =H10*(1+0.039) -> 1845.264 | I18: =I10*(1+0.088) -> 2144.448 | J18: =J10*(1+-0.024) -> 1276.608 | K18: =K10*(1+0.047) -> 1876.224 | L18: =L10*(1+0.031) -> 1416.594 | M18: =M10*(1+-0.068) -> 1802.488 | N18: =SUM(B18:M18) -> 28676.344
A19: Contracted Labor | B19: =B11*(1+0.094) -> 3354.204 | C19: =C11*(1+-0.027) -> 2150.33 | D19: =D11*(1+0.063) -> 2365.175 | E19: =E11*(1+0.038) -> 1783.284 | F19: =F11*(1+-0.091) -> 1727.1 | G19: =G11*(1+0.017) -> 4086.306 | H19: =H11*(1+0.052) -> 3266.46 | I19: =I11*(1+-0.044) -> 2850.792 | J19: =J11*(1+0.083) -> 1729.551 | K19: =K11*(1+0.021) -> 3432.602 | L19: =L11*(1+0.068) -> 1677.828 | M19: =M11*(1+-0.039) -> 2168.016 | N19: =SUM(B19:M19) -> 30591.648
A20: Miscellaneous Vendor | B20: =B12*(1+-0.033) -> 4047.862 | C20: =C12*(1+0.086) -> 3344.88 | D20: =D12*(1+0.021) -> 2876.157 | E20: =E12*(1+0.057) -> 3404.597 | F20: =F12*(1+-0.048) -> 3543.344 | G20: =G12*(1+0.093) -> 3835.337 | H20: =H12*(1+0.014) -> 1804.92 | I20: =I12*(1+-0.062) -> 1084.328 | J20: =J12*(1+0.077) -> 2211.081 | K20: =K12*(1+0.039) -> 1976.178 | L20: =L12*(1+-0.017) -> 1692.726 | M20: =M12*(1+0.101) -> 4445.838 | N20: =SUM(B20:M20) -> 34267.248
A22: Variance $ | B22: Jan | C22: Feb | D22: Mar | E22: Apr | F22: May | G22: Jun | H22: Jul | I22: Aug | J22: Sep | K22: Oct | L22: Nov | M22: Dec | N22: FY Total
A23: Vendor Licensing | B23: =B15-B7 -> 156.978 | C23: =C15-C7 -> -43.092 | D23: =D15-D7 -> 180.95 | E23: =E15-E7 -> 47.547 | F23: =F15-F7 -> -220.09 | G23: =G15-G7 -> 265.268 | H23: =H15-H7 -> 62.032 | I23: =I15-I7 -> -55.86 | ... M23: =M15-M7 -> 297.248 | N23: =SUM(B23:M23) -> 865.428
A24: Professional Services | B24: =B16-B8 -> -21.641 | C24: =C16-C8 -> 122.932 | D24: =D16-D8 -> 118.218 | E24: =E16-E8 -> -150.066 | F24: =F16-F8 -> 159.432 | G24: =G16-G8 -> 64.218 | H24: =H16-H8 -> 242.272 | I24: =I16-I8 -> -33.356 | ... M24: =M16-M8 -> 68.024 | N24: =SUM(B24:M24) -> 618.293
A25: Software & Platforms | B25: =B17-B9 -> 355.221 | C25: =C17-C9 -> 29.68 | D25: =D17-D9 -> -70.148 | E25: =E17-E9 -> 130.656 | F25: =F17-F9 -> 104.608 | G25: =G17-G9 -> -109.705 | H25: =H17-H9 -> 292.248 | I25: =I17-I9 -> 144.609 | ... M25: =M17-M9 -> -198.871 | N25: =SUM(B25:M25) -> 866.754
A26: Infrastructure & Hosting | B26: =B18-B10 -> 84.617 | C26: =C18-C10 -> 313.144 | D26: =D18-D10 -> -155.021 | E26: =E18-E10 -> 48.994 | F26: =F18-F10 -> 249.584 | G26: =G18-G10 -> -63.6 | H26: =H18-H10 -> 69.264 | I26: =I18-I10 -> 173.448 | ... M26: =M18-M10 -> -131.512 | N26: =SUM(B26:M26) -> 684.344
A27: Contracted Labor | B27: =B19-B11 -> 288.204 | C27: =C19-C11 -> -59.67 | D27: =D19-D11 -> 140.175 | E27: =E19-E11 -> 65.284 | F27: =F19-F11 -> -172.9 | G27: =G19-G11 -> 68.306 | H27: =H19-H11 -> 161.46 | I27: =I19-I11 -> -131.208 | ... M27: =M19-M11 -> -87.984 | N27: =SUM(B27:M27) -> 581.648
A28: Miscellaneous Vendor | B28: =B20-B12 -> -138.138 | C28: =C20-C12 -> 264.88 | D28: =D20-D12 -> 59.157 | E28: =E20-E12 -> 183.597 | F28: =F20-F12 -> -178.656 | G28: =G20-G12 -> 326.337 | H28: =H20-H12 -> 24.92 | I28: =I20-I12 -> -71.672 | ... M28: =M20-M12 -> 407.838 | N28: =SUM(B28:M28) -> 1081.248
A30: Variance % | B30: Jan | C30: Feb | D30: Mar | E30: Apr | F30: May | G30: Jun | H30: Jul | I30: Aug | J30: Sep | K30: Oct | L30: Nov | M30: Dec | N30: FY Total
A31: Vendor Licensing | B31: =IFERROR(B23/B7,0) -> 0.051 | C31: =IFERROR(C23/C7,0) -> -0.038 | D31: =IFERROR(D23/D7,0) -> 0.094 | E31: =IFERROR(E23/E7,0) -> 0.027 | F31: =IFERROR(F23/F7,0) -> -0.065 | G31: =IFERROR(G23/G7,0) -> 0.083 | H31: =IFERROR(H23/H7,0) -> 0.016 | I31: =IFERROR(I23/I7,0) -> -0.042 | ... N31: =IFERROR(N23/N7,0) -> 0.031324309
A32: Professional Services | B32: =IFERROR(B24/B8,0) -> -0.019 | C32: =IFERROR(C24/C8,0) -> 0.073 | D32: =IFERROR(D24/D8,0) -> 0.038 | E32: =IFERROR(E24/E8,0) -> -0.054 | F32: =IFERROR(F24/F8,0) -> 0.091 | G32: =IFERROR(G24/G8,0) -> 0.022 | H32: =IFERROR(H24/H8,0) -> 0.067 | I32: =IFERROR(I24/I8,0) -> -0.031 | ... N32: =IFERROR(N24/N8,0) -> 0.021602019
A33: Software & Platforms | B33: =IFERROR(B25/B9,0) -> 0.087 | C33: =IFERROR(C25/C9,0) -> 0.014 | D33: =IFERROR(D25/D9,0) -> -0.052 | E33: =IFERROR(E25/E9,0) -> 0.096 | F33: =IFERROR(F25/F9,0) -> 0.028 | G33: =IFERROR(G25/G9,0) -> -0.037 | H33: =IFERROR(H25/H9,0) -> 0.081 | I33: =IFERROR(I25/I9,0) -> 0.043 | ... N33: =IFERROR(N25/N9,0) -> 0.025107294
A34: Infrastructure & Hosting | B34: =IFERROR(B26/B10,0) -> 0.023 | C34: =IFERROR(C26/C10,0) -> 0.104 | D34: =IFERROR(D26/D10,0) -> -0.041 | E34: =IFERROR(E26/E10,0) -> 0.017 | F34: =IFERROR(F26/F10,0) -> 0.076 | G34: =IFERROR(G26/G10,0) -> -0.053 | H34: =IFERROR(H26/H10,0) -> 0.039 | I34: =IFERROR(I26/I10,0) -> 0.088 | ... N34: =IFERROR(N26/N10,0) -> 0.024447842
A35: Contracted Labor | B35: =IFERROR(B27/B11,0) -> 0.094 | C35: =IFERROR(C27/C11,0) -> -0.027 | D35: =IFERROR(D27/D11,0) -> 0.063 | E35: =IFERROR(E27/E11,0) -> 0.038 | F35: =IFERROR(F27/F11,0) -> -0.091 | G35: =IFERROR(G27/G11,0) -> 0.017 | H35: =IFERROR(H27/H11,0) -> 0.052 | I35: =IFERROR(I27/I11,0) -> -0.044 | ... N35: =IFERROR(N27/N11,0) -> 0.019381806
A36: Miscellaneous Vendor | B36: =IFERROR(B28/B12,0) -> -0.033 | C36: =IFERROR(C28/C12,0) -> 0.086 | D36: =IFERROR(D28/D12,0) -> 0.021 | E36: =IFERROR(E28/E12,0) -> 0.057 | F36: =IFERROR(F28/F12,0) -> -0.048 | G36: =IFERROR(G28/G12,0) -> 0.093 | H36: =IFERROR(H28/H12,0) -> 0.014 | I36: =IFERROR(I28/I12,0) -> -0.062 | ... N36: =IFERROR(N28/N12,0) -> 0.03258145
A38: Note: Actual figures calculated as Budget × (1 + monthly variance rate). Variance rates are synthetic demonstration values embedded in formulas. In a production model these would be sourced from the GL and stored in a separate assumptions table with reconciliation controls.

Sheet Consolidation Scenarios
A1: VENDOR CONSOLIDATION — SCENARIO ANALYSIS
A2: Toggle assumptions (blue cells) to model different consolidation strategies | $M
A3: MODEL ASSUMPTIONS — CHANGE BLUE CELLS TO TOGGLE SCENARIOS
A4: Assumption | B4: Value | C4: Notes
A5: Vendor Reduction Target % | B5: 0.62 | C5: % of current vendor roster to eliminate
A6: Year 1 Transition Cost ($M) | B6: 4.2 | C6: One-time migration, renegotiation, integration cost
A7: Year 2 Run-Rate Savings Capture % | B7: 0.85 | C7: Year 2 savings capture (ramp period)
A8: Year 3 Full Savings Capture % | B8: 1 | C8: Year 3 full steady-state savings
A9: Risk Contingency Reserve ($M) | B9: 2.5 | C9: Reserve for contract dispute / remediation
A10: Renegotiation Discount Rate | B10: 0.18 | C10: Average discount achieved via volume consolidation
A11: Total Enterprise Vendor Baseline ($M) | B11: 428.6 | C11: Finance + Risk + Operations combined
A13: TRANSITION COST ASSUMPTIONS | Split: 60% Year 1 · 28% Year 2 · 12% Year 3
A14: Parameter | B14: Scenario A (Conservative) | C14: Scenario B (Base Case) | D14: Scenario C (Aggressive) | E14: Notes
A15: Transition Cost as % of Gross Savings | B15: 0.15 | C15: 0.12 | D15: 0.18 | E15: A:15% less leverage B:12% optimal efficiency C:18% tail vendor complexity
A16: Total Transition Cost ($M) | B16: =B15*B31 -> 21.3 | C16: =C15*C31 -> 21.648 | D16: =D15*D31 -> 37.566 | E16: Gross savings × TC% (auto-calculated)
A17: Year 1 TC ($M) — 60% | B17: =B16*0.6 -> 12.78 | C17: =C16*0.6 -> 12.9888 | D17: =D16*0.6 -> 22.5396 | E17: Migrations, legal, contract exits
A18: Year 2 TC ($M) — 28% | B18: =B16*0.28 -> 5.964 | C18: =C16*0.28 -> 6.06144 | D18: =D16*0.28 -> 10.51848 | E18: Remaining migrations, change management
A19: Year 3 TC ($M) — 12% | B19: =B16*0.12 -> 2.556 | C19: =C16*0.12 -> 2.59776 | D19: =D16*0.12 -> 4.50792 | E19: Tail cleanup and residual items
A21: SAVINGS CAPTURE RATES | Scenario B references shared assumption cells above
A22: Parameter | B22: Scenario A (Conservative) | C22: Scenario B (Base Case) | D22: Scenario C (Aggressive) | E22: Notes
A23: Year 1 Savings Capture % | B23: 0.6 | C23: =$B$7 -> 0.85 | D23: 0.9 | E23: % of gross savings captured in Year 1
A24: Year 2 Savings Capture % | B24: 0.75 | C24: =$B$7 -> 0.85 | D24: 0.95 | E24: Ramp-period capture rate
A25: Year 3 Savings Capture % | B25: 0.9 | C25: =$B$8 -> 1 | D25: 1 | E25: Full steady-state capture
A26: Risk Contingency ($M) | B26: 4 | C26: =$B$9 -> 2.5 | D26: 1.8 | E26: Reserve for disputes/remediation
A28: SCENARIO OUTPUT — 3-YEAR MODEL | All outputs formula-driven from assumptions above
A29: Metric | B29: Scenario A (Conservative) | C29: Scenario B (Base Case — RECOMMENDED) | D29: Scenario C (Aggressive) | E29: Notes
A30: Vendors Reduced | B30: 47 → 28 | C30: 47 → 18 | D30: 47 → 12 | E30: Scope of consolidation
A31: Gross Savings Identified ($M) | B31: 142 | C31: 180.4 | D31: 208.7 | E31: Full run-rate at Year 3 — scenario anchor inputs (blue = change to model)
A32: Transition Cost % of Gross | B32: =B15 -> 0.15 | C32: =C15 -> 0.12 | D32: =D15 -> 0.18 | E32: From TC assumptions above
A33: Total Transition Cost ($M) | B33: =B16 -> 21.3 | C33: =C16 -> 21.648 | D33: =D16 -> 37.566 | E33: From TC assumptions above
A34: Year 1 Net Savings ($M) | B34: =B31*B23-B17 -> 72.42 | C34: =C31*C23-C17 -> 140.3512 | D34: =D31*D23-D17 -> 165.2904 | E34: Gross × Y1 capture % − Y1 transition cost
A35: Year 2 Net Savings ($M) | B35: =B31*B24-B18 -> 100.536 | C35: =C31*C24-C18 -> 147.27856 | D35: =D31*D24-D18 -> 187.74652 | E35: Gross × Y2 capture % − Y2 transition cost
A36: Year 3 Net Savings ($M) | B36: =B31*B25-B19 -> 125.244 | C36: =C31*C25-C19 -> 177.80224 | D36: =D31*D25-D19 -> 204.19208 | E36: Gross × Y3 capture % − Y3 transition cost
A37: 3-Year Cumulative Net Savings ($M) | B37: =B34+B35+B36 -> 298.2 | C37: =C34+C35+C36 -> 465.432 | D37: =D34+D35+D36 -> 557.229 | E37: Y1+Y2+Y3 net savings — transition costs already deducted in each year
A38: Risk Contingency Reserve ($M) | B38: =-B26 -> -4 | C38: =-C26 -> -2.5 | D38: =-D26 -> -1.8 | E38: Reserve held — reduces net program value
A39: Net Program Value ($M) | B39: =B37+B38 -> 294.2 | C39: =C37+C38 -> 462.932 | D39: =D37+D38 -> 555.429 | E39: 3-year cumulative net of contingency reserve
A40: 3-Year ROI Multiple | B40: =IFERROR(B37/B33,0) -> 14 | C40: =IFERROR(C37/C33,0) -> 21.5 | D40: =IFERROR(D37/D33,0) -> 14.833333 | E40: Cumulative net ÷ total TC | B has highest ROI — this is why it is recommended
A41: Break-Even (months) | B41: =IF(B33<=0,"N/A",IF(B34>=B33,ROUNDUP(B33/(B34/12),0),IF(B34+B35>=B33,12+ROUNDUP((B33-B34)/(B35/12),0),24+ROUNDUP((B33-B34-B35)/(B36/12),0)))) -> 4 | C41: =IF(C33<=0,"N/A",IF(C34>=C33,ROUNDUP(C33/(C34/12),0),IF(C34+C35>=C33,12+ROUNDUP((C33-C34)/(C35/12),0),24+ROUNDUP((C33-C34-C35)/(C36/12),0)))) -> 2 | D41: =IF(D33<=0,"N/A",IF(D34>=D33,ROUNDUP(D33/(D34/12),0),IF(D34+D35>=D33,12+ROUNDUP((D33-D34)/(D35/12),0),24+ROUNDUP((D33-D34-D35)/(D36/12),0)))) -> 3 | E41: Multi-year: months until cumulative net savings recovers total transition cost
A43: WHY SCENARIO B IS RECOMMENDED: Fastest break-even (2 months) AND highest 3-year ROI multiple (21.5x). Scenario C generates more gross savings but the 18% TC rate (tail vendor complexity) reduces ROI to 14.8x. Scenario A is lowest risk but weakest ROI (14.0x). Scenario B is the optimal balance of impact, cost, and efficiency.

Sheet Sensitivity Model
A1: SENSITIVITY ANALYSIS — NET SAVINGS vs. KEY VARIABLES
A2: Two-variable sensitivity: Vendor Reduction % vs. Renegotiation Discount Rate | $M net savings
A3: How to use: Change the blue assumption cells on the Consolidation Scenarios tab. This table auto-recalculates to show how net program value changes across a range of vendor reduction and discount rate combinations.
A5: NET SAVINGS SENSITIVITY TABLE ($M)
A6: Vendor Reduction % ↓ Discount Rate → | B6: 0.1 | C6: 0.12 | D6: 0.14 | E6: 0.16 | F6: 0.18 | G6: 0.2 | H6: 0.22
A7: 0.4 | B7: ='Consolidation Scenarios'!$B$11*$A7*B$6-'Consolidation Scenarios'!$B$6 -> 12.944 | C7: ='Consolidation Scenarios'!$B$11*$A7*C$6-'Consolidation Scenarios'!$B$6 -> 16.3728 | D7: ='Consolidation Scenarios'!$B$11*$A7*D$6-'Consolidation Scenarios'!$B$6 -> 19.8016 | E7: ='Consolidation Scenarios'!$B$11*$A7*E$6-'Consolidation Scenarios'!$B$6 -> 23.2304 | F7: ='Consolidation Scenarios'!$B$11*$A7*F$6-'Consolidation Scenarios'!$B$6 -> 26.6592 | G7: ='Consolidation Scenarios'!$B$11*$A7*G$6-'Consolidation Scenarios'!$B$6 -> 30.088 | H7: ='Consolidation Scenarios'!$B$11*$A7*H$6-'Consolidation Scenarios'!$B$6 -> 33.5168
A8: 0.45 | B8: ='Consolidation Scenarios'!$B$11*$A8*B$6-'Consolidation Scenarios'!$B$6 -> 15.087 | C8: ='Consolidation Scenarios'!$B$11*$A8*C$6-'Consolidation Scenarios'!$B$6 -> 18.9444 | D8: ='Consolidation Scenarios'!$B$11*$A8*D$6-'Consolidation Scenarios'!$B$6 -> 22.8018 | E8: ='Consolidation Scenarios'!$B$11*$A8*E$6-'Consolidation Scenarios'!$B$6 -> 26.6592 | F8: ='Consolidation Scenarios'!$B$11*$A8*F$6-'Consolidation Scenarios'!$B$6 -> 30.5166 | G8: ='Consolidation Scenarios'!$B$11*$A8*G$6-'Consolidation Scenarios'!$B$6 -> 34.374 | H8: ='Consolidation Scenarios'!$B$11*$A8*H$6-'Consolidation Scenarios'!$B$6 -> 38.2314
A9: 0.5 | B9: ='Consolidation Scenarios'!$B$11*$A9*B$6-'Consolidation Scenarios'!$B$6 -> 17.23 | C9: ='Consolidation Scenarios'!$B$11*$A9*C$6-'Consolidation Scenarios'!$B$6 -> 21.516 | D9: ='Consolidation Scenarios'!$B$11*$A9*D$6-'Consolidation Scenarios'!$B$6 -> 25.802 | E9: ='Consolidation Scenarios'!$B$11*$A9*E$6-'Consolidation Scenarios'!$B$6 -> 30.088 | F9: ='Consolidation Scenarios'!$B$11*$A9*F$6-'Consolidation Scenarios'!$B$6 -> 34.374 | G9: ='Consolidation Scenarios'!$B$11*$A9*G$6-'Consolidation Scenarios'!$B$6 -> 38.66 | H9: ='Consolidation Scenarios'!$B$11*$A9*H$6-'Consolidation Scenarios'!$B$6 -> 42.946
A10: 0.55 | B10: ='Consolidation Scenarios'!$B$11*$A10*B$6-'Consolidation Scenarios'!$B$6 -> 19.373 | C10: ='Consolidation Scenarios'!$B$11*$A10*C$6-'Consolidation Scenarios'!$B$6 -> 24.0876 | D10: ='Consolidation Scenarios'!$B$11*$A10*D$6-'Consolidation Scenarios'!$B$6 -> 28.8022 | E10: ='Consolidation Scenarios'!$B$11*$A10*E$6-'Consolidation Scenarios'!$B$6 -> 33.5168 | F10: ='Consolidation Scenarios'!$B$11*$A10*F$6-'Consolidation Scenarios'!$B$6 -> 38.2314 | G10: ='Consolidation Scenarios'!$B$11*$A10*G$6-'Consolidation Scenarios'!$B$6 -> 42.946 | H10: ='Consolidation Scenarios'!$B$11*$A10*H$6-'Consolidation Scenarios'!$B$6 -> 47.6606
A11: 0.62 | B11: ='Consolidation Scenarios'!$B$11*$A11*B$6-'Consolidation Scenarios'!$B$6 -> 22.3732 | C11: ='Consolidation Scenarios'!$B$11*$A11*C$6-'Consolidation Scenarios'!$B$6 -> 27.68784 | D11: ='Consolidation Scenarios'!$B$11*$A11*D$6-'Consolidation Scenarios'!$B$6 -> 33.00248 | E11: ='Consolidation Scenarios'!$B$11*$A11*E$6-'Consolidation Scenarios'!$B$6 -> 38.31712 | F11: ='Consolidation Scenarios'!$B$11*$A11*F$6-'Consolidation Scenarios'!$B$6 -> 43.63176 | G11: ='Consolidation Scenarios'!$B$11*$A11*G$6-'Consolidation Scenarios'!$B$6 -> 48.9464 | H11: ='Consolidation Scenarios'!$B$11*$A11*H$6-'Consolidation Scenarios'!$B$6 -> 54.26104
A12: 0.7 | B12: ='Consolidation Scenarios'!$B$11*$A12*B$6-'Consolidation Scenarios'!$B$6 -> 25.802 | C12: ='Consolidation Scenarios'!$B$11*$A12*C$6-'Consolidation Scenarios'!$B$6 -> 31.8024 | D12: ='Consolidation Scenarios'!$B$11*$A12*D$6-'Consolidation Scenarios'!$B$6 -> 37.8028 | E12: ='Consolidation Scenarios'!$B$11*$A12*E$6-'Consolidation Scenarios'!$B$6 -> 43.8032 | F12: ='Consolidation Scenarios'!$B$11*$A12*F$6-'Consolidation Scenarios'!$B$6 -> 49.8036 | G12: ='Consolidation Scenarios'!$B$11*$A12*G$6-'Consolidation Scenarios'!$B$6 -> 55.804 | H12: ='Consolidation Scenarios'!$B$11*$A12*H$6-'Consolidation Scenarios'!$B$6 -> 61.8044
A13: 0.75 | B13: ='Consolidation Scenarios'!$B$11*$A13*B$6-'Consolidation Scenarios'!$B$6 -> 27.945 | C13: ='Consolidation Scenarios'!$B$11*$A13*C$6-'Consolidation Scenarios'!$B$6 -> 34.374 | D13: ='Consolidation Scenarios'!$B$11*$A13*D$6-'Consolidation Scenarios'!$B$6 -> 40.803 | E13: ='Consolidation Scenarios'!$B$11*$A13*E$6-'Consolidation Scenarios'!$B$6 -> 47.232 | F13: ='Consolidation Scenarios'!$B$11*$A13*F$6-'Consolidation Scenarios'!$B$6 -> 53.661 | G13: ='Consolidation Scenarios'!$B$11*$A13*G$6-'Consolidation Scenarios'!$B$6 -> 60.09 | H13: ='Consolidation Scenarios'!$B$11*$A13*H$6-'Consolidation Scenarios'!$B$6 -> 66.519
A15: LEGEND
A16: $55M+ High impact
A17: $40M–$54M Target range
A18: $25M–$39M Acceptable
A19: Below $25M Review assumptions
A20: Highlighted cell = Scenario B (62% reduction, 18% discount)
A22: Formula: Net Savings = Total Enterprise Baseline × Vendor Reduction % × Renegotiation Discount Rate − Transition Cost. All cells reference live assumption inputs on the Consolidation Scenarios tab. Change the Vendor Reduction % (B5) or Renegotiation Discount Rate (B10) on that tab to see the full sensitivity range update automatically.
